snippetchecker/__init__.py
snippetchecker/api.py
snippetchecker/support.py
snippetchecker/scripts/__init__.py
snippetchecker/scripts/initial.py
snippetchecker_api-0.1.0.dist-info/LICENSE
snippetchecker_api-0.1.0.dist-info/METADATA
snippetchecker_api-0.1.0.dist-info/WHEEL
snippetchecker_api-0.1.0.dist-info/top_level.txt
snippetchecker_api-0.1.0.dist-info/RECORD
